CHANGELOG.md
CONTRIBUTING.md
LICENSE
MANIFEST.in
README.md
setup.py
icepaposc/__init__.py
icepaposc/__main__.py
icepaposc/axis_time.py
icepaposc/channel.py
icepaposc/collector.py
icepaposc/curve_item.py
icepaposc/dialog_settings.py
icepaposc/settings.py
icepaposc/window_main.py
icepaposc.egg-info/PKG-INFO
icepaposc.egg-info/SOURCES.txt
icepaposc.egg-info/dependency_links.txt
icepaposc.egg-info/entry_points.txt
icepaposc.egg-info/requires.txt
icepaposc.egg-info/top_level.txt
icepaposc/custom_widgets/__init__.py
icepaposc/custom_widgets/square_radiobtn.py
icepaposc/ui/__init__.py
icepaposc/ui/dialog_settings.ui
icepaposc/ui/resources_rc.py
icepaposc/ui/window_main.ui
icepaposc/ui/icons/__init__.py