Metadata-Version: 2.1
Name: icepaposc
Version: 0.10.3
Summary: Python IcePAP Extension
Home-page: https://github.com/ALBA-Synchrotron/IcepapOCS
Author: Jarkko Inki and Roberto Homs-Puron
Author-email: ctbeamlines@cells.es
License: GPL
Keywords: APP
Classifier: Development Status :: 5 - Production/Stable
Classifier: Intended Audience :: Developers
Classifier: Intended Audience :: End Users/Desktop
Classifier: License :: OSI Approved :: GNU General Public License v3 (GPLv3)
Classifier: Natural Language :: English
Classifier: Operating System :: POSIX
Classifier: Operating System :: Microsoft :: Windows
Classifier: Programming Language :: Python :: 3.5
Classifier: Topic :: Communications
Classifier: Topic :: Software Development :: Libraries
Requires-Python: >=3.5
License-File: LICENSE
Requires-Dist: PyQt5
Requires-Dist: icepap>=3.6.1
Requires-Dist: pyqtgraph
Requires-Dist: numpy
